{
  "total_capital_usd": 3000.0,
  "min_edge": 0.03,
  "buy_min_edge": 0.04,
  "sell_min_edge": 0.04,
  "buy_min_price": 0.15,
  "sell_max_price": 0.85,
  "sizing_mode": "flat",
  "flat_amount_usd": 50.0,
  "max_open_positions": 500,
  "enable_scenario_risk": true,
  "scenario_min_positions": 10,
  "scenario_reduce_size_to_fit": true,
  "scenario_use_bates_probabilities": true,
  "scenario_price_range_pct": 0.15,
  "scenario_price_step": 250.0,
  "scenario_time_step_hours": 4.0,
  "scenario_require_expected_pnl_improvement": true,
  "scenario_max_surface_flatness": null,
  "scenario_min_max_loss": null,
  "poll_interval_seconds": 5.0,
  "positions_path": "data/strategy/positions.ec2.json",
  "paper_trades_path": "data/strategy/paper_trades.ec2.csv"
}
